unisci/__init__.py
unisci/_conversion_factors.py
unisci/_error.py
unisci/constants.py
unisci/conversion_factors.py
unisci/error.py
unisci/metric.py
unisci/types.py
unisci/formulas/__init__.py
unisci/formulas/_validation.py
unisci/formulas/chemistry.py
unisci/periodic/periodic-table-lookup.json
unisci/periodic/periodic-table-numbers.json
unisci/periodic/periodic-table-symbols.json
unisci-1.7.0.dist-info/LICENSE
unisci-1.7.0.dist-info/METADATA
unisci-1.7.0.dist-info/WHEEL
unisci-1.7.0.dist-info/top_level.txt
unisci-1.7.0.dist-info/RECORD
