Metadata-Version: 2.1
Name: unisci
Version: 1.7.0
Summary: Units Conversions, and Science Package
Author: Vivaan Singhvi
Author-email: singhvi.vivaan@gmail.com
License: MIT
Project-URL: Documentation, https://unisci.readthedocs.io/en/latest/
Requires-Python: >=3.8
License-File: LICENSE
Requires-Dist: sympy (==1.11.1)
Requires-Dist: typing (==3.7.4.3)
